LICENSE
MANIFEST.in
README.md
pyproject.toml
setup.py
blog/__init__.py
blog/admin.py
blog/apps.py
blog/models.py
blog/tests.py
blog/urls.py
blog/views.py
sitio/__init__.py
sitio/asgi.py
sitio/settings.py
sitio/urls.py
sitio/wsgi.py
sitio.egg-info/PKG-INFO
sitio.egg-info/SOURCES.txt
sitio.egg-info/dependency_links.txt
sitio.egg-info/not-zip-safe
sitio.egg-info/requires.txt
sitio.egg-info/top_level.txt