Metadata-Version: 2.1
Name: sitio
Version: 0.5
Summary: desenvolvido por Cleyson Cassio para proporcionar uma experiência online interativa e informativa para os membros da academia.
Home-page: https://github.com/cleysoncassio/Rocks-Fit.git
Author: Cleyson Cassio
Author-email: cleysoncassio@gmail.com
License: BSD
Classifier: Development Status :: 5 - Production/Stable
Classifier: Environment :: Web Environment
Classifier: Intended Audience :: Developers
Classifier: License :: OSI Approved :: BSD License
Classifier: Operating System :: OS Independent
Classifier: Programming Language :: Python
Classifier: Programming Language :: Python :: 3.9
Classifier: Topic :: Internet :: WWW/HTTP
Classifier: Framework :: Pytest
License-File: LICENSE
Requires-Dist: Django>=5.0.7
Requires-Dist: Pillow
Requires-Dist: pytest
Requires-Dist: pytest-django
Requires-Dist: python-decouple
Requires-Dist: django-admin-interface
Requires-Dist: django-colorfield
Requires-Dist: django-crispy-forms
Requires-Dist: django-debug-toolbar
Requires-Dist: django-extensions
Requires-Dist: django-filter
Requires-Dist: django-image-cropping
Requires-Dist: django-storages
Requires-Dist: django-taggit
Requires-Dist: django-taggit-autosuggest
Requires-Dist: django-taggit-serializer
Requires-Dist: django-widget-tweaks
Requires-Dist: gunicorn
Requires-Dist: psycopg2-binary
Requires-Dist: whitenoise
Requires-Dist: dj-database-url
Requires-Dist: dj-static
Requires-Dist: boto3
Requires-Dist: django-storages[boto3]
Requires-Dist: django-storages[google]
Requires-Dist: django-storages[azure]
